destofr_words/GamePlayer.ui
destofr_words/__init__.py
destofr_words/__main__.py
destofr_words/main.css
destofr_words-0.0.1.data/data/share/applications/io.github.destofr.Words.desktop
destofr_words-0.0.1.dist-info/COPYING
destofr_words-0.0.1.dist-info/METADATA
destofr_words-0.0.1.dist-info/WHEEL
destofr_words-0.0.1.dist-info/top_level.txt
destofr_words-0.0.1.dist-info/RECORD
