Metadata-Version: 2.1
Name: destofr_words
Version: 0.0.1
Summary: Word guessing game inspired by Wordle
Home-page: https://github.com/destofr/words
Author: destofr
Author-email: destofr@outlook.com
License: GPLv3+
Project-URL: Bug Tracker, https://github.com/destofr/words/issues
Platform: UNKNOWN
Classifier: Environment :: X11 Applications :: GTK
Classifier: Intended Audience :: End Users/Desktop
Classifier: License :: OSI Approved :: GNU General Public License v3 or later (GPLv3+)
Classifier: Operating System :: POSIX :: Linux
Classifier: Programming Language :: Python :: 3
Classifier: Topic :: Games/Entertainment
License-File: COPYING
